scrapper_helpers/__init__.py
scrapper_helpers/utils.py
scrapper_helpers-0.2.0.dist-info/DESCRIPTION.rst
scrapper_helpers-0.2.0.dist-info/METADATA
scrapper_helpers-0.2.0.dist-info/RECORD
scrapper_helpers-0.2.0.dist-info/WHEEL
scrapper_helpers-0.2.0.dist-info/metadata.json
scrapper_helpers-0.2.0.dist-info/top_level.txt
