Metadata-Version: 2.0
Name: scrapper-helpers
Version: 0.2.0
Summary: Scrapper helpers
Home-page: https://github.com/limebrains/scrapper-helpers
Author: LimeBrains
Author-email: mail@limebrains.com
License: UNKNOWN
Platform: UNKNOWN
